{
    "delete": {
        "baseline": {
            "cpu_util": 0.0,
            "disk_read": 0.6195502281188965,
            "disk_write": 4.286737442016602,
            "disk_used": 3.975879669189453,
            "disk_free": 24.026195526123047,
            "virtual_used": 1.2202529907226562,
            "virtual_free": 2.5267066955566406
        },
        "samples": [
            {
                "cpu_util": 0.0,
                "disk_read": 0.6195502281188965,
                "disk_write": 4.286741256713867,
                "disk_used": 3.9758834838867188,
                "disk_free": 24.02619171142578,
                "virtual_used": 1.2202529907226562,
                "virtual_free": 2.5267066955566406,
                "sample": 1
            }
        ],
        "response_time": 0.0010921955108642578
    },
    "create": {
        "baseline": {
            "cpu_util": 0.0,
            "disk_read": 0.6195502281188965,
            "disk_write": 4.286741256713867,
            "disk_used": 3.9758834838867188,
            "disk_free": 24.02619171142578,
            "virtual_used": 1.2202491760253906,
            "virtual_free": 2.5267105102539062
        },
        "samples": [
            {
                "cpu_util": 4.8,
                "disk_read": 0.6195502281188965,
                "disk_write": 4.286890029907227,
                "disk_used": 3.97589111328125,
                "disk_free": 24.02618408203125,
                "virtual_used": 1.2202491760253906,
                "virtual_free": 2.5267105102539062,
                "sample": 1
            }
        ],
        "response_time": 0.01996779441833496
    },
    "updateOneStruct": {
        "baseline": {
            "cpu_util": 0.0,
            "disk_read": 0.6195502281188965,
            "disk_write": 4.286920547485352,
            "disk_used": 3.97589111328125,
            "disk_free": 24.02618408203125,
            "virtual_used": 1.220245361328125,
            "virtual_free": 2.526714324951172
        },
        "samples": [
            {
                "cpu_util": 0.0,
                "disk_read": 0.6195502281188965,
                "disk_write": 4.286924362182617,
                "disk_used": 3.97589111328125,
                "disk_free": 24.02618408203125,
                "virtual_used": 1.2188758850097656,
                "virtual_free": 2.5280838012695312,
                "sample": 1
            }
        ],
        "response_time": 0.0021772384643554688
    }
}