{
    "delete": {
        "baseline": {
            "cpu_util": 0.0,
            "disk_read": 0.3482065200805664,
            "disk_write": 4.407564163208008,
            "disk_used": 3.966480255126953,
            "disk_free": 24.035594940185547,
            "virtual_used": 2.2298583984375,
            "virtual_free": 1.5171012878417969
        },
        "samples": [
            {
                "cpu_util": 0.0,
                "disk_read": 0.3482065200805664,
                "disk_write": 4.407567977905273,
                "disk_used": 3.966480255126953,
                "disk_free": 24.035594940185547,
                "virtual_used": 2.2298507690429688,
                "virtual_free": 1.5171089172363281,
                "sample": 1
            }
        ],
        "response_time": 0.0009696483612060547
    },
    "create": {
        "baseline": {
            "cpu_util": 0.0,
            "disk_read": 0.3482065200805664,
            "disk_write": 4.407567977905273,
            "disk_used": 3.966480255126953,
            "disk_free": 24.035594940185547,
            "virtual_used": 2.2298507690429688,
            "virtual_free": 1.5171089172363281
        },
        "samples": [
            {
                "cpu_util": 50.0,
                "disk_read": 0.3482065200805664,
                "disk_write": 4.407567977905273,
                "disk_used": 3.966480255126953,
                "disk_free": 24.035594940185547,
                "virtual_used": 2.2298507690429688,
                "virtual_free": 1.5171089172363281,
                "sample": 1
            },
            {
                "cpu_util": 47.8,
                "disk_read": 0.3482065200805664,
                "disk_write": 4.407716751098633,
                "disk_used": 3.966480255126953,
                "disk_free": 24.035594940185547,
                "virtual_used": 2.2298507690429688,
                "virtual_free": 1.5171089172363281,
                "sample": 2
            },
            {
                "cpu_util": 51.5,
                "disk_read": 0.3482065200805664,
                "disk_write": 4.407716751098633,
                "disk_used": 3.966480255126953,
                "disk_free": 24.035594940185547,
                "virtual_used": 2.2298507690429688,
                "virtual_free": 1.5171089172363281,
                "sample": 3
            },
            {
                "cpu_util": 53.8,
                "disk_read": 0.3482065200805664,
                "disk_write": 4.407716751098633,
                "disk_used": 3.966480255126953,
                "disk_free": 24.035594940185547,
                "virtual_used": 2.2298507690429688,
                "virtual_free": 1.5171089172363281,
                "sample": 4
            },
            {
                "cpu_util": 50.0,
                "disk_read": 0.3482065200805664,
                "disk_write": 4.407716751098633,
                "disk_used": 3.966480255126953,
                "disk_free": 24.035594940185547,
                "virtual_used": 2.2298507690429688,
                "virtual_free": 1.5171089172363281,
                "sample": 5
            },
            {
                "cpu_util": 51.9,
                "disk_read": 0.3482065200805664,
                "disk_write": 4.407716751098633,
                "disk_used": 3.966480255126953,
                "disk_free": 24.035594940185547,
                "virtual_used": 2.230571746826172,
                "virtual_free": 1.516387939453125,
                "sample": 6
            },
            {
                "cpu_util": 36.4,
                "disk_read": 0.3482065200805664,
                "disk_write": 4.407892227172852,
                "disk_used": 3.9664878845214844,
                "disk_free": 24.035587310791016,
                "virtual_used": 2.246227264404297,
                "virtual_free": 1.500732421875,
                "sample": 7
            },
            {
                "cpu_util": 52.6,
                "disk_read": 0.3482065200805664,
                "disk_write": 4.409856796264648,
                "disk_used": 3.9664878845214844,
                "disk_free": 24.035587310791016,
                "virtual_used": 2.2476959228515625,
                "virtual_free": 1.4992637634277344,
                "sample": 8
            },
            {
                "cpu_util": 52.2,
                "disk_read": 0.3482065200805664,
                "disk_write": 4.412580490112305,
                "disk_used": 3.96649169921875,
                "disk_free": 24.03558349609375,
                "virtual_used": 2.2496871948242188,
                "virtual_free": 1.4972724914550781,
                "sample": 9
            },
            {
                "cpu_util": 50.0,
                "disk_read": 0.3482065200805664,
                "disk_write": 4.41493034362793,
                "disk_used": 3.96649169921875,
                "disk_free": 24.03558349609375,
                "virtual_used": 2.245594024658203,
                "virtual_free": 1.5013656616210938,
                "sample": 10
            },
            {
                "cpu_util": 100.0,
                "disk_read": 0.3482065200805664,
                "disk_write": 4.417291641235352,
                "disk_used": 3.9722747802734375,
                "disk_free": 24.029800415039062,
                "virtual_used": 2.267963409423828,
                "virtual_free": 1.4789962768554688,
                "sample": 11
            },
            {
                "cpu_util": 60.9,
                "disk_read": 0.3482065200805664,
                "disk_write": 4.417291641235352,
                "disk_used": 3.9766693115234375,
                "disk_free": 24.025405883789062,
                "virtual_used": 2.3108901977539062,
                "virtual_free": 1.4360694885253906,
                "sample": 12
            },
            {
                "cpu_util": 50.0,
                "disk_read": 0.3482065200805664,
                "disk_write": 4.41960334777832,
                "disk_used": 3.9766693115234375,
                "disk_free": 24.025405883789062,
                "virtual_used": 2.284587860107422,
                "virtual_free": 1.462371826171875,
                "sample": 13
            },
            {
                "cpu_util": 52.0,
                "disk_read": 0.3482065200805664,
                "disk_write": 4.421991348266602,
                "disk_used": 3.9766693115234375,
                "disk_free": 24.025405883789062,
                "virtual_used": 2.3027992248535156,
                "virtual_free": 1.4441604614257812,
                "sample": 14
            },
            {
                "cpu_util": 52.6,
                "disk_read": 0.3482065200805664,
                "disk_write": 4.424505233764648,
                "disk_used": 3.9766693115234375,
                "disk_free": 24.025405883789062,
                "virtual_used": 2.2749710083007812,
                "virtual_free": 1.4719886779785156,
                "sample": 15
            },
            {
                "cpu_util": 68.2,
                "disk_read": 0.3482065200805664,
                "disk_write": 4.426412582397461,
                "disk_used": 3.97772216796875,
                "disk_free": 24.02435302734375,
                "virtual_used": 2.2773056030273438,
                "virtual_free": 1.4696540832519531,
                "sample": 16
            },
            {
                "cpu_util": 100.0,
                "disk_read": 0.3482065200805664,
                "disk_write": 4.426664352416992,
                "disk_used": 3.9850082397460938,
                "disk_free": 24.017066955566406,
                "virtual_used": 2.3092803955078125,
                "virtual_free": 1.4376792907714844,
                "sample": 17
            },
            {
                "cpu_util": 52.4,
                "disk_read": 0.3482065200805664,
                "disk_write": 4.427427291870117,
                "disk_used": 3.9865074157714844,
                "disk_free": 24.015567779541016,
                "virtual_used": 2.3204498291015625,
                "virtual_free": 1.4265098571777344,
                "sample": 18
            },
            {
                "cpu_util": 57.1,
                "disk_read": 0.3482065200805664,
                "disk_write": 4.43077278137207,
                "disk_used": 3.9865074157714844,
                "disk_free": 24.015567779541016,
                "virtual_used": 2.3177833557128906,
                "virtual_free": 1.4291763305664062,
                "sample": 19
            },
            {
                "cpu_util": 56.5,
                "disk_read": 0.3482065200805664,
                "disk_write": 4.431344985961914,
                "disk_used": 3.9865074157714844,
                "disk_free": 24.015567779541016,
                "virtual_used": 2.3164215087890625,
                "virtual_free": 1.4305381774902344,
                "sample": 20
            },
            {
                "cpu_util": 50.0,
                "disk_read": 0.3482065200805664,
                "disk_write": 4.435014724731445,
                "disk_used": 3.9865074157714844,
                "disk_free": 24.015567779541016,
                "virtual_used": 2.3202438354492188,
                "virtual_free": 1.4267158508300781,
                "sample": 21
            },
            {
                "cpu_util": 61.9,
                "disk_read": 0.3482065200805664,
                "disk_write": 4.436002731323242,
                "disk_used": 3.9878005981445312,
                "disk_free": 24.01427459716797,
                "virtual_used": 2.317798614501953,
                "virtual_free": 1.4291610717773438,
                "sample": 22
            },
            {
                "cpu_util": 84.2,
                "disk_read": 0.3482065200805664,
                "disk_write": 4.436639785766602,
                "disk_used": 3.9971389770507812,
                "disk_free": 24.00493621826172,
                "virtual_used": 2.3650779724121094,
                "virtual_free": 1.3818817138671875,
                "sample": 23
            },
            {
                "cpu_util": 52.4,
                "disk_read": 0.3482065200805664,
                "disk_write": 4.440286636352539,
                "disk_used": 3.9971389770507812,
                "disk_free": 24.00493621826172,
                "virtual_used": 2.3617324829101562,
                "virtual_free": 1.3852272033691406,
                "sample": 24
            },
            {
                "cpu_util": 66.7,
                "disk_read": 0.3482065200805664,
                "disk_write": 4.440698623657227,
                "disk_used": 3.9971389770507812,
                "disk_free": 24.00493621826172,
                "virtual_used": 2.3598899841308594,
                "virtual_free": 1.3870697021484375,
                "sample": 25
            },
            {
                "cpu_util": 52.6,
                "disk_read": 0.3482065200805664,
                "disk_write": 4.443288803100586,
                "disk_used": 3.9971389770507812,
                "disk_free": 24.00493621826172,
                "virtual_used": 2.362010955810547,
                "virtual_free": 1.38494873046875,
                "sample": 26
            },
            {
                "cpu_util": 50.0,
                "disk_read": 0.3482065200805664,
                "disk_write": 4.445398330688477,
                "disk_used": 3.9971389770507812,
                "disk_free": 24.00493621826172,
                "virtual_used": 2.3679275512695312,
                "virtual_free": 1.3790321350097656,
                "sample": 27
            },
            {
                "cpu_util": 95.2,
                "disk_read": 0.3482065200805664,
                "disk_write": 4.469743728637695,
                "disk_used": 4.007289886474609,
                "disk_free": 23.99478530883789,
                "virtual_used": 2.4081268310546875,
                "virtual_free": 1.3388328552246094,
                "sample": 28
            },
            {
                "cpu_util": 52.6,
                "disk_read": 0.3482065200805664,
                "disk_write": 4.471494674682617,
                "disk_used": 4.007289886474609,
                "disk_free": 23.99478530883789,
                "virtual_used": 2.4051055908203125,
                "virtual_free": 1.3418540954589844,
                "sample": 29
            },
            {
                "cpu_util": 50.0,
                "disk_read": 0.3482065200805664,
                "disk_write": 4.473649978637695,
                "disk_used": 4.007289886474609,
                "disk_free": 23.99478530883789,
                "virtual_used": 2.4349136352539062,
                "virtual_free": 1.3120460510253906,
                "sample": 30
            },
            {
                "cpu_util": 52.6,
                "disk_read": 0.3482065200805664,
                "disk_write": 4.474931716918945,
                "disk_used": 4.007289886474609,
                "disk_free": 23.99478530883789,
                "virtual_used": 2.4072189331054688,
                "virtual_free": 1.3397407531738281,
                "sample": 31
            },
            {
                "cpu_util": 73.9,
                "disk_read": 0.3482065200805664,
                "disk_write": 4.477956771850586,
                "disk_used": 4.008750915527344,
                "disk_free": 23.993324279785156,
                "virtual_used": 2.409149169921875,
                "virtual_free": 1.3378105163574219,
                "sample": 32
            },
            {
                "cpu_util": 57.9,
                "disk_read": 0.3482065200805664,
                "disk_write": 4.478384017944336,
                "disk_used": 4.016883850097656,
                "disk_free": 23.985191345214844,
                "virtual_used": 2.4325485229492188,
                "virtual_free": 1.3144111633300781,
                "sample": 33
            }
        ],
        "response_time": 9.205703735351562
    },
    "insertOneStruct": {
        "baseline": {
            "cpu_util": 0.0,
            "disk_read": 0.3482065200805664,
            "disk_write": 4.478384017944336,
            "disk_used": 4.016883850097656,
            "disk_free": 23.985191345214844,
            "virtual_used": 2.4300689697265625,
            "virtual_free": 1.3168907165527344
        },
        "samples": [
            {
                "cpu_util": 0.0,
                "disk_read": 0.3482065200805664,
                "disk_write": 4.478387832641602,
                "disk_used": 4.016883850097656,
                "disk_free": 23.985191345214844,
                "virtual_used": 2.4303016662597656,
                "virtual_free": 1.3166580200195312,
                "sample": 1
            }
        ],
        "response_time": 0.0008900165557861328
    }
}