{
    "delete": {
        "baseline": {
            "cpu_util": 0.0,
            "disk_read": 0.8918776512145996,
            "disk_write": 16.206998825073242,
            "disk_used": 4.986515045166016,
            "disk_free": 23.015560150146484,
            "virtual_used": 1.8145980834960938,
            "virtual_free": 1.9323539733886719
        },
        "samples": [
            {
                "cpu_util": 0.0,
                "disk_read": 0.8918776512145996,
                "disk_write": 16.207002639770508,
                "disk_used": 4.986515045166016,
                "disk_free": 23.015560150146484,
                "virtual_used": 1.8145980834960938,
                "virtual_free": 1.9323539733886719,
                "sample": 1
            }
        ],
        "response_time": 0.0008933544158935547
    },
    "create": {
        "baseline": {
            "cpu_util": 0.0,
            "disk_read": 0.8918776512145996,
            "disk_write": 16.207002639770508,
            "disk_used": 4.986515045166016,
            "disk_free": 23.015560150146484,
            "virtual_used": 1.8145980834960938,
            "virtual_free": 1.9323539733886719
        },
        "samples": [
            {
                "cpu_util": 50.0,
                "disk_read": 0.8918776512145996,
                "disk_write": 16.207002639770508,
                "disk_used": 4.986515045166016,
                "disk_free": 23.015560150146484,
                "virtual_used": 1.8145980834960938,
                "virtual_free": 1.9323539733886719,
                "sample": 1
            },
            {
                "cpu_util": 47.4,
                "disk_read": 0.8918776512145996,
                "disk_write": 16.21181297302246,
                "disk_used": 4.986522674560547,
                "disk_free": 23.015552520751953,
                "virtual_used": 1.8020057678222656,
                "virtual_free": 1.9449462890625,
                "sample": 2
            },
            {
                "cpu_util": 28.6,
                "disk_read": 0.8918776512145996,
                "disk_write": 16.215280532836914,
                "disk_used": 4.9865264892578125,
                "disk_free": 23.015548706054688,
                "virtual_used": 1.8059806823730469,
                "virtual_free": 1.9409713745117188,
                "sample": 3
            }
        ],
        "response_time": 0.6099255084991455
    },
    "insertOneUnstruct": {
        "baseline": {
            "cpu_util": 0.0,
            "disk_read": 0.8918776512145996,
            "disk_write": 16.21656608581543,
            "disk_used": 4.9865264892578125,
            "disk_free": 23.015548706054688,
            "virtual_used": 1.8059501647949219,
            "virtual_free": 1.9410018920898438
        },
        "samples": [
            {
                "cpu_util": 0.0,
                "disk_read": 0.8918776512145996,
                "disk_write": 16.216569900512695,
                "disk_used": 4.9865264892578125,
                "disk_free": 23.015548706054688,
                "virtual_used": 1.8059501647949219,
                "virtual_free": 1.9410018920898438,
                "sample": 1
            }
        ],
        "response_time": 0.0009236335754394531
    }
}