{
    "delete": {
        "baseline": {
            "cpu_util": 0.0,
            "disk_read": 0.3253755569458008,
            "disk_write": 0.6769886016845703,
            "disk_used": 3.8120765686035156,
            "disk_free": 24.189998626708984,
            "virtual_used": 0.61651611328125,
            "virtual_free": 1.2493515014648438
        },
        "samples": [
            {
                "cpu_util": 4.8,
                "disk_read": 0.3253755569458008,
                "disk_write": 0.6769924163818359,
                "disk_used": 3.8120765686035156,
                "disk_free": 24.189998626708984,
                "virtual_used": 0.61651611328125,
                "virtual_free": 1.2493515014648438,
                "sample": 1
            }
        ],
        "response_time": 0.0009293556213378906
    },
    "create": {
        "baseline": {
            "cpu_util": 0.0,
            "disk_read": 0.3253755569458008,
            "disk_write": 0.6769924163818359,
            "disk_used": 3.8120765686035156,
            "disk_free": 24.189998626708984,
            "virtual_used": 0.61651611328125,
            "virtual_free": 1.2493515014648438
        },
        "samples": [
            {
                "cpu_util": 38.1,
                "disk_read": 0.3253755569458008,
                "disk_write": 0.6781024932861328,
                "disk_used": 3.812084197998047,
                "disk_free": 24.189990997314453,
                "virtual_used": 0.6180305480957031,
                "virtual_free": 1.2478370666503906,
                "sample": 1
            }
        ],
        "response_time": 0.08438992500305176
    },
    "insertOneUnstruct": {
        "baseline": {
            "cpu_util": 0.0,
            "disk_read": 0.3253755569458008,
            "disk_write": 0.6781024932861328,
            "disk_used": 3.812084197998047,
            "disk_free": 24.189990997314453,
            "virtual_used": 0.618743896484375,
            "virtual_free": 1.2471237182617188
        },
        "samples": [
            {
                "cpu_util": 4.8,
                "disk_read": 0.3253755569458008,
                "disk_write": 0.6781063079833984,
                "disk_used": 3.812084197998047,
                "disk_free": 24.189990997314453,
                "virtual_used": 0.618743896484375,
                "virtual_free": 1.2471237182617188,
                "sample": 1
            }
        ],
        "response_time": 0.0014183521270751953
    }
}