{
    "delete": {
        "baseline": {
            "cpu_util": 0.0,
            "disk_read": 0.34246397018432617,
            "disk_write": 3.083833694458008,
            "disk_used": 3.92578125,
            "disk_free": 24.0762939453125,
            "virtual_used": 1.102935791015625,
            "virtual_free": 2.6440200805664062
        },
        "samples": [
            {
                "cpu_util": 0.0,
                "disk_read": 0.34246397018432617,
                "disk_write": 3.0838375091552734,
                "disk_used": 3.92578125,
                "disk_free": 24.0762939453125,
                "virtual_used": 1.102935791015625,
                "virtual_free": 2.6440200805664062,
                "sample": 1
            }
        ],
        "response_time": 0.0009124279022216797
    },
    "create": {
        "baseline": {
            "cpu_util": 0.0,
            "disk_read": 0.34246397018432617,
            "disk_write": 3.0838375091552734,
            "disk_used": 3.92578125,
            "disk_free": 24.0762939453125,
            "virtual_used": 1.102935791015625,
            "virtual_free": 2.6440200805664062
        },
        "samples": [
            {
                "cpu_util": 0.0,
                "disk_read": 0.34246397018432617,
                "disk_write": 3.0840015411376953,
                "disk_used": 3.925792694091797,
                "disk_free": 24.076282501220703,
                "virtual_used": 1.1029167175292969,
                "virtual_free": 2.6440391540527344,
                "sample": 1
            }
        ],
        "response_time": 0.014806509017944336
    },
    "insertOneThenUpdateTimestampUnstruct": {
        "baseline": {
            "cpu_util": 0.0,
            "disk_read": 0.34246397018432617,
            "disk_write": 3.0840396881103516,
            "disk_used": 3.925792694091797,
            "disk_free": 24.076282501220703,
            "virtual_used": 1.1029052734375,
            "virtual_free": 2.6440505981445312
        },
        "samples": [
            {
                "cpu_util": 0.0,
                "disk_read": 0.34246397018432617,
                "disk_write": 3.084043502807617,
                "disk_used": 3.925792694091797,
                "disk_free": 24.076282501220703,
                "virtual_used": 1.1028861999511719,
                "virtual_free": 2.6440696716308594,
                "sample": 1
            }
        ],
        "response_time": 0.0014388561248779297
    }
}